{
  "run_date": "2026-04-28T22:57:53.290738",
  "risk": "high",
  "top_funds_overall": [
    {
      "scheme_name": "SBI Small Cap Fund - Direct Plan - Growth",
      "scheme_category": "SBI Small Cap Fund - Direct Plan - Growth",
      "broad_category": "Equity",
      "aum_cr": 22555.6034,
      "score": 100.0,
      "aum_bonus": 0.0,
      "cagr": 0.2419575506113969,
      "alpha": 0.1281169160272595,
      "sortino_ratio": 1.0185313898320567,
      "volatility": 0.1523064234784849,
      "max_drawdown": -0.4026012761687717,
      "calmar_ratio": 0.6009855530362689,
      "rolling_1y_positive_ratio": 0.8241563055062167,
      "rolling_cagr_consistency": 0.7643007863184162,
      "downside_deviation_stability": 0.9972541815112121,
      "return_variance_stability": 0.9999315127480622,
      "excess_cagr_vs_benchmark": 0.12733803935633548,
      "benchmark_outperformance_ratio": 0.5274220032840723
    },
    {
      "scheme_name": "SBI Balanced Advantage Fund - Direct Plan - Growth",
      "scheme_category": "Hybrid Scheme - Dynamic Asset Allocation or Balanced Advantage",
      "broad_category": "Hybrid",
      "aum_cr": 35454.3902,
      "score": 95.12239290374715,
      "aum_bonus": 3.1223929037471594,
      "cagr": 0.11312899990552161,
      "alpha": 0.04221099675730876,
      "sortino_ratio": 0.7426830630451609,
      "volatility": 0.06342222751210964,
      "max_drawdown": -0.07392584359999058,
      "calmar_ratio": 1.530303807118625,
      "rolling_1y_positive_ratio": 1.0,
      "rolling_cagr_consistency": 0.9278015843127725,
      "downside_deviation_stability": 0.9991593741209488,
      "return_variance_stability": 0.9999918545427345,
      "excess_cagr_vs_benchmark": 0.03881287806925604,
      "benchmark_outperformance_ratio": 0.5180616740088105
    },
    {
      "scheme_name": "Nippon India Small Cap Fund - Direct Plan Growth Plan - Growth Option",
      "scheme_category": "Nippon India Small Cap Fund - Direct Plan Growth Plan - Growth Option",
      "broad_category": "Equity",
      "aum_cr": 45272.2292,
      "score": 88.34194429999691,
      "aum_bonus": 5.472839750306163,
      "cagr": 0.23981403725341965,
      "alpha": 0.12471592225722114,
      "sortino_ratio": 0.8702236926911293,
      "volatility": 0.17421768765735224,
      "max_drawdown": -0.4858371846504487,
      "calmar_ratio": 0.49360988584264426,
      "rolling_1y_positive_ratio": 0.8127068166776968,
      "rolling_cagr_consistency": 0.7231889432422406,
      "downside_deviation_stability": 0.9966404853294569,
      "return_variance_stability": 0.999896033963602,
      "excess_cagr_vs_benchmark": 0.1314276742477578,
      "benchmark_outperformance_ratio": 0.5371165644171779
    },
    {
      "scheme_name": "Kotak Midcap Fund - Direct Plan - Growth",
      "scheme_category": "Equity Scheme - Mid Cap Fund",
      "broad_category": "Equity",
      "aum_cr": 44328.543399999995,
      "score": 87.31820315987497,
      "aum_bonus": 5.270291208371017,
      "cagr": 0.2023044947500212,
      "alpha": 0.09318840539612191,
      "sortino_ratio": 0.8008249276458614,
      "volatility": 0.15412439922806595,
      "max_drawdown": -0.3597117768161001,
      "calmar_ratio": 0.5624072042919179,
      "rolling_1y_positive_ratio": 0.8666004634227077,
      "rolling_cagr_consistency": 0.7752855708091503,
      "downside_deviation_stability": 0.9968410076619146,
      "return_variance_stability": 0.9999092346098744,
      "excess_cagr_vs_benchmark": 0.09305877814518859,
      "benchmark_outperformance_ratio": 0.5397361153728137
    },
    {
      "scheme_name": "Aditya Birla Sun Life Savings Fund - Growth - Direct Plan",
      "scheme_category": "Debt Scheme - Ultra Short Duration Fund",
      "broad_category": "Debt",
      "aum_cr": 7823.9556999999995,
      "score": 82.0,
      "aum_bonus": 0.0,
      "cagr": 0.07695680874239086,
      "alpha": 0.017035666468247855,
      "sortino_ratio": 1.5368976789981106,
      "volatility": 0.006475922020121026,
      "max_drawdown": -0.012080617487131618,
      "calmar_ratio": 6.370271124333333,
      "rolling_1y_positive_ratio": 1.0,
      "rolling_cagr_consistency": 0.9824259733158142,
      "downside_deviation_stability": 0.9998327383845295,
      "return_variance_stability": 0.9999995375224077,
      "excess_cagr_vs_benchmark": -0.021511710060182043,
      "benchmark_outperformance_ratio": 0.4809255784865541
    },
    {
      "scheme_name": "Kotak Multicap Fund-Direct Plan-Growth",
      "scheme_category": "Equity Scheme - Multi Cap Fund",
      "broad_category": "Equity",
      "aum_cr": 19360.156499999997,
      "score": 71.47280957081014,
      "aum_bonus": 0.0,
      "cagr": 0.17585588638772043,
      "alpha": 0.10124666281743525,
      "sortino_ratio": 0.6579446202857921,
      "volatility": 0.15770806830764733,
      "max_drawdown": -0.20996357098926047,
      "calmar_ratio": 0.8375542745780189,
      "rolling_1y_positive_ratio": 0.9493087557603687,
      "rolling_cagr_consistency": 0.8250369191325425,
      "downside_deviation_stability": 0.9976393189675897,
      "return_variance_stability": 0.99994761424681,
      "excess_cagr_vs_benchmark": 0.1121633158380888,
      "benchmark_outperformance_ratio": 0.5510752688172043
    },
    {
      "scheme_name": "SBI EQUITY HYBRID FUND - DIRECT PLAN - Growth",
      "scheme_category": "SBI EQUITY HYBRID FUND - DIRECT PLAN - Growth",
      "broad_category": "Hybrid",
      "aum_cr": 72494.8446,
      "score": 69.84200184790285,
      "aum_bonus": 10.0,
      "cagr": 0.14455898431892322,
      "alpha": 0.04618045786868752,
      "sortino_ratio": 0.6713968407574081,
      "volatility": 0.11172549883899903,
      "max_drawdown": -0.2748953179124069,
      "calmar_ratio": 0.525869212385006,
      "rolling_1y_positive_ratio": 0.9326732673267327,
      "rolling_cagr_consistency": 0.8763797688517692,
      "downside_deviation_stability": 0.9972999313103631,
      "return_variance_stability": 0.9999164899629682,
      "excess_cagr_vs_benchmark": 0.034720146495285986,
      "benchmark_outperformance_ratio": 0.5223926380368098
    },
    {
      "scheme_name": "HDFC Mid Cap Fund - Growth Option - Direct Plan",
      "scheme_category": "HDFC Mid Cap Fund - Growth Option - Direct Plan",
      "broad_category": "Equity",
      "aum_cr": 24347.242000000002,
      "score": 62.42059797950333,
      "aum_bonus": 0.0,
      "cagr": 0.20313640450106862,
      "alpha": 0.09194039545203017,
      "sortino_ratio": 0.7889837929943638,
      "volatility": 0.15719128233440693,
      "max_drawdown": -0.39513231480613614,
      "calmar_ratio": 0.5140971691994706,
      "rolling_1y_positive_ratio": 0.8617724867724867,
      "rolling_cagr_consistency": 0.7862886493929799,
      "downside_deviation_stability": 0.9968880121896512,
      "return_variance_stability": 0.9999058845211571,
      "excess_cagr_vs_benchmark": 0.09334622187566977,
      "benchmark_outperformance_ratio": 0.5386266094420601
    },
    {
      "scheme_name": "SBI MIDCAP FUND - DIRECT PLAN - GROWTH",
      "scheme_category": "Equity Scheme - Mid Cap Fund",
      "broad_category": "Equity",
      "aum_cr": 17302.2366,
      "score": 60.304681351440486,
      "aum_bonus": 0.0,
      "cagr": 0.18462284806612206,
      "alpha": 0.08042143291950699,
      "sortino_ratio": 0.7271911381185169,
      "volatility": 0.152174407967285,
      "max_drawdown": -0.43051182543750455,
      "calmar_ratio": 0.42884500995646385,
      "rolling_1y_positive_ratio": 0.8254701418673706,
      "rolling_cagr_consistency": 0.7765754646954963,
      "downside_deviation_stability": 0.9970344197729345,
      "return_variance_stability": 0.999912540752789,
      "excess_cagr_vs_benchmark": 0.07516359993675259,
      "benchmark_outperformance_ratio": 0.5314320760502913
    },
    {
      "scheme_name": "Kotak Bond Short Term Plan-(Growth) - Direct",
      "scheme_category": "Debt Scheme - Short Duration Fund",
      "broad_category": "Debt",
      "aum_cr": 14817.926599999999,
      "score": 54.474756443349726,
      "aum_bonus": 0.0,
      "cagr": 0.07946961561945654,
      "alpha": 0.018908618947707755,
      "sortino_ratio": 0.8993145780907156,
      "volatility": 0.017734681670344372,
      "max_drawdown": -0.03054739886926411,
      "calmar_ratio": 2.6015182490518534,
      "rolling_1y_positive_ratio": 1.0,
      "rolling_cagr_consistency": 0.9761579959608053,
      "downside_deviation_stability": 0.9994373911483441,
      "return_variance_stability": 0.9999965422559949,
      "excess_cagr_vs_benchmark": -0.018976421733900795,
      "benchmark_outperformance_ratio": 0.480450422270879
    },
    {
      "scheme_name": "Aditya Birla Sun Life Money Manager Fund - Growth - Direct Plan",
      "scheme_category": "Debt Scheme - Money Market Fund",
      "broad_category": "Debt",
      "aum_cr": 21974.3854,
      "score": 52.49747997883174,
      "aum_bonus": 0.0,
      "cagr": 0.07398123230519449,
      "alpha": 0.0029405784572221066,
      "sortino_ratio": 0.5927660854115682,
      "volatility": 0.005257572171567117,
      "max_drawdown": -0.014003169243528187,
      "calmar_ratio": 5.283177759162357,
      "rolling_1y_positive_ratio": 1.0,
      "rolling_cagr_consistency": 0.986708835881466,
      "downside_deviation_stability": 0.9998745813773046,
      "return_variance_stability": 0.9999994732980387,
      "excess_cagr_vs_benchmark": -0.04230937224587428,
      "benchmark_outperformance_ratio": 0.4785714285714286
    },
    {
      "scheme_name": "HDFC Corporate Bond Fund - Growth Option - Direct Plan",
      "scheme_category": "HDFC Corporate Bond Fund - Growth Option - Direct Plan",
      "broad_category": "Debt",
      "aum_cr": 25623.636000000002,
      "score": 49.78276313292757,
      "aum_bonus": 0.0,
      "cagr": 0.07941206015503899,
      "alpha": 0.01877136192198027,
      "sortino_ratio": 0.8763350749212109,
      "volatility": 0.017780864143134817,
      "max_drawdown": -0.040034480917253486,
      "calmar_ratio": 1.9835916024282738,
      "rolling_1y_positive_ratio": 1.0,
      "rolling_cagr_consistency": 0.9743821886120838,
      "downside_deviation_stability": 0.9994704233419466,
      "return_variance_stability": 0.9999971578674725,
      "excess_cagr_vs_benchmark": -0.019270385849034177,
      "benchmark_outperformance_ratio": 0.4807752422632072
    },
    {
      "scheme_name": "SBI LARGE & MIDCAP FUND -DIRECT PLAN -Growth",
      "scheme_category": "Equity Scheme - Large & Mid Cap Fund",
      "broad_category": "Equity",
      "aum_cr": 28203.478,
      "score": 45.43256036522666,
      "aum_bonus": 0.9223926160602878,
      "cagr": 0.16643201109801042,
      "alpha": 0.05642324722027772,
      "sortino_ratio": 0.6391900824416523,
      "volatility": 0.1512239770514898,
      "max_drawdown": -0.3642776614336253,
      "calmar_ratio": 0.45688228710762124,
      "rolling_1y_positive_ratio": 0.8999669858038957,
      "rolling_cagr_consistency": 0.8294439722871484,
      "downside_deviation_stability": 0.9968576709295588,
      "return_variance_stability": 0.9999002871487596,
      "excess_cagr_vs_benchmark": 0.055982254167977974,
      "benchmark_outperformance_ratio": 0.5332924209880331
    },
    {
      "scheme_name": "Nippon India Growth Mid Cap Fund - Direct Plan Growth Plan - Growth Option",
      "scheme_category": "Nippon India Growth Mid Cap Fund - Direct Plan Growth Plan - Growth Option",
      "broad_category": "Equity",
      "aum_cr": 32525.0541,
      "score": 44.37471269588963,
      "aum_bonus": 2.2932012556698025,
      "cagr": 0.1843195009186549,
      "alpha": 0.07438631103958449,
      "sortino_ratio": 0.6621434092473638,
      "volatility": 0.16894197019650503,
      "max_drawdown": -0.35323117372404966,
      "calmar_ratio": 0.5218098362480558,
      "rolling_1y_positive_ratio": 0.8600727753886868,
      "rolling_cagr_consistency": 0.7966651130472628,
      "downside_deviation_stability": 0.9969354493067316,
      "return_variance_stability": 0.9999079940312646,
      "excess_cagr_vs_benchmark": 0.07578984921061105,
      "benchmark_outperformance_ratio": 0.5280588776448942
    },
    {
      "scheme_name": "Nippon India Money Market Fund - Direct Plan Growth Plan - Growth Option",
      "scheme_category": "Nippon India Money Market Fund - Direct Plan Growth Plan - Growth Option",
      "broad_category": "Debt",
      "aum_cr": 5089.2908,
      "score": 43.67245235963694,
      "aum_bonus": 0.0,
      "cagr": 0.07312921796644911,
      "alpha": 0.0024161158184175385,
      "sortino_ratio": 0.6347123333451428,
      "volatility": 0.003993342644543456,
      "max_drawdown": -0.008672644107707007,
      "calmar_ratio": 8.432170980181501,
      "rolling_1y_positive_ratio": 1.0,
      "rolling_cagr_consistency": 0.985740440421616,
      "downside_deviation_stability": 0.99991664087694,
      "return_variance_stability": 0.9999997835710532,
      "excess_cagr_vs_benchmark": -0.04168748712609016,
      "benchmark_outperformance_ratio": 0.478895096213532
    },
    {
      "scheme_name": "CANARA ROBECO LARGE AND MID CAP FUND - DIRECT PLAN - GROWTH OPTION",
      "scheme_category": "CANARA ROBECO LARGE AND MID CAP FUND - DIRECT PLAN - GROWTH OPTION",
      "broad_category": "Equity",
      "aum_cr": 18757.6568,
      "score": 41.623975517785155,
      "aum_bonus": 0.0,
      "cagr": 0.19062695172993793,
      "alpha": 0.07847197482905888,
      "sortino_ratio": 0.7076023042254337,
      "volatility": 0.1649259863770014,
      "max_drawdown": -0.3619945379261739,
      "calmar_ratio": 0.5266017349930702,
      "rolling_1y_positive_ratio": 0.8590803837247767,
      "rolling_cagr_consistency": 0.7710101923589534,
      "downside_deviation_stability": 0.9965451738349046,
      "return_variance_stability": 0.9998758400145685,
      "excess_cagr_vs_benchmark": 0.08240215902099846,
      "benchmark_outperformance_ratio": 0.524685679239497
    },
    {
      "scheme_name": "SBI FOCUSED FUND - DIRECT PLAN -GROWTH",
      "scheme_category": "Equity Scheme - Focused Fund",
      "broad_category": "Equity",
      "aum_cr": 29636.1554,
      "score": 40.29967437921648,
      "aum_bonus": 1.3988277604891328,
      "cagr": 0.15749844559936643,
      "alpha": 0.05386242864674767,
      "sortino_ratio": 0.6610694365150082,
      "volatility": 0.13618112604083826,
      "max_drawdown": -0.32738405163804885,
      "calmar_ratio": 0.481081606789736,
      "rolling_1y_positive_ratio": 0.8623308022449654,
      "rolling_cagr_consistency": 0.8350057490281538,
      "downside_deviation_stability": 0.9971191876036767,
      "return_variance_stability": 0.9999124217660691,
      "excess_cagr_vs_benchmark": 0.04426299895019592,
      "benchmark_outperformance_ratio": 0.5250076710647438
    },
    {
      "scheme_name": "ICICI Prudential Money Market Fund Option - Direct Plan -  Growth",
      "scheme_category": "ICICI Prudential Money Market Fund Option - Direct Plan -  Growth",
      "broad_category": "Debt",
      "aum_cr": 8209.6115,
      "score": 39.2048124607189,
      "aum_bonus": 0.0,
      "cagr": 0.07269394452181266,
      "alpha": 0.0019994040177216676,
      "sortino_ratio": 0.5631949065683358,
      "volatility": 0.004779826192439494,
      "max_drawdown": -0.012282069428827126,
      "calmar_ratio": 5.91870490091787,
      "rolling_1y_positive_ratio": 1.0,
      "rolling_cagr_consistency": 0.9868197575548294,
      "downside_deviation_stability": 0.9998921230377519,
      "return_variance_stability": 0.9999995912486189,
      "excess_cagr_vs_benchmark": -0.04333471220568219,
      "benchmark_outperformance_ratio": 0.4788819875776398
    },
    {
      "scheme_name": "Kotak Arbitrage Fund - Direct Plan - Growth",
      "scheme_category": "Hybrid Scheme - Arbitrage Fund",
      "broad_category": "Hybrid",
      "aum_cr": 27307.923199999997,
      "score": 36.225486880833074,
      "aum_bonus": 0.6121231060458379,
      "cagr": 0.0708544352494398,
      "alpha": 0.011572348811365228,
      "sortino_ratio": 1.229140115608729,
      "volatility": 0.00998572628047568,
      "max_drawdown": -0.0056836872072952025,
      "calmar_ratio": 10.0,
      "rolling_1y_positive_ratio": 1.0,
      "rolling_cagr_consistency": 0.983499661747419,
      "downside_deviation_stability": 0.9998887446375072,
      "return_variance_stability": 0.9999997830880518,
      "excess_cagr_vs_benchmark": -0.04258971997617711,
      "benchmark_outperformance_ratio": 0.47560222359481164
    },
    {
      "scheme_name": "SBI Multicap Fund- Direct Plan- Growth option",
      "scheme_category": "Equity Scheme - Multi Cap Fund",
      "broad_category": "Equity",
      "aum_cr": 20632.2074,
      "score": 33.45620736824841,
      "aum_bonus": 0.0,
      "cagr": 0.13753276445348228,
      "alpha": 0.04962943963630034,
      "sortino_ratio": 0.5847732759667371,
      "volatility": 0.12254882281385304,
      "max_drawdown": -0.15112501305597847,
      "calmar_ratio": 0.9100595703673391,
      "rolling_1y_positive_ratio": 0.9609375,
      "rolling_cagr_consistency": 0.8819620349151643,
      "downside_deviation_stability": 0.9984302712351738,
      "return_variance_stability": 0.9999703108142451,
      "excess_cagr_vs_benchmark": 0.050387958541030065,
      "benchmark_outperformance_ratio": 0.5307539682539683
    }
  ],
  "top_funds_by_broad_category": {
    "Equity": [
      {
        "scheme_name": "SBI Small Cap Fund - Direct Plan - Growth",
        "scheme_category": "SBI Small Cap Fund - Direct Plan - Growth",
        "broad_category": "Equity",
        "aum_cr": 22555.6034,
        "score": 100.0,
        "aum_bonus": 0.0,
        "cagr": 0.2419575506113969,
        "alpha": 0.1281169160272595,
        "sortino_ratio": 1.0185313898320567,
        "volatility": 0.1523064234784849,
        "max_drawdown": -0.4026012761687717,
        "calmar_ratio": 0.6009855530362689,
        "rolling_1y_positive_ratio": 0.8241563055062167,
        "rolling_cagr_consistency": 0.7643007863184162,
        "downside_deviation_stability": 0.9972541815112121,
        "return_variance_stability": 0.9999315127480622,
        "excess_cagr_vs_benchmark": 0.12733803935633548,
        "benchmark_outperformance_ratio": 0.5274220032840723
      },
      {
        "scheme_name": "Nippon India Small Cap Fund - Direct Plan Growth Plan - Growth Option",
        "scheme_category": "Nippon India Small Cap Fund - Direct Plan Growth Plan - Growth Option",
        "broad_category": "Equity",
        "aum_cr": 45272.2292,
        "score": 88.34194429999691,
        "aum_bonus": 5.472839750306163,
        "cagr": 0.23981403725341965,
        "alpha": 0.12471592225722114,
        "sortino_ratio": 0.8702236926911293,
        "volatility": 0.17421768765735224,
        "max_drawdown": -0.4858371846504487,
        "calmar_ratio": 0.49360988584264426,
        "rolling_1y_positive_ratio": 0.8127068166776968,
        "rolling_cagr_consistency": 0.7231889432422406,
        "downside_deviation_stability": 0.9966404853294569,
        "return_variance_stability": 0.999896033963602,
        "excess_cagr_vs_benchmark": 0.1314276742477578,
        "benchmark_outperformance_ratio": 0.5371165644171779
      },
      {
        "scheme_name": "HDFC Mid Cap Fund - Growth Option - Direct Plan",
        "scheme_category": "HDFC Mid Cap Fund - Growth Option - Direct Plan",
        "broad_category": "Equity",
        "aum_cr": 24347.242000000002,
        "score": 62.42059797950333,
        "aum_bonus": 0.0,
        "cagr": 0.20313640450106862,
        "alpha": 0.09194039545203017,
        "sortino_ratio": 0.7889837929943638,
        "volatility": 0.15719128233440693,
        "max_drawdown": -0.39513231480613614,
        "calmar_ratio": 0.5140971691994706,
        "rolling_1y_positive_ratio": 0.8617724867724867,
        "rolling_cagr_consistency": 0.7862886493929799,
        "downside_deviation_stability": 0.9968880121896512,
        "return_variance_stability": 0.9999058845211571,
        "excess_cagr_vs_benchmark": 0.09334622187566977,
        "benchmark_outperformance_ratio": 0.5386266094420601
      },
      {
        "scheme_name": "Kotak Midcap Fund - Direct Plan - Growth",
        "scheme_category": "Equity Scheme - Mid Cap Fund",
        "broad_category": "Equity",
        "aum_cr": 44328.543399999995,
        "score": 87.31820315987497,
        "aum_bonus": 5.270291208371017,
        "cagr": 0.2023044947500212,
        "alpha": 0.09318840539612191,
        "sortino_ratio": 0.8008249276458614,
        "volatility": 0.15412439922806595,
        "max_drawdown": -0.3597117768161001,
        "calmar_ratio": 0.5624072042919179,
        "rolling_1y_positive_ratio": 0.8666004634227077,
        "rolling_cagr_consistency": 0.7752855708091503,
        "downside_deviation_stability": 0.9968410076619146,
        "return_variance_stability": 0.9999092346098744,
        "excess_cagr_vs_benchmark": 0.09305877814518859,
        "benchmark_outperformance_ratio": 0.5397361153728137
      },
      {
        "scheme_name": "Kotak Multicap Fund-Direct Plan-Growth",
        "scheme_category": "Equity Scheme - Multi Cap Fund",
        "broad_category": "Equity",
        "aum_cr": 19360.156499999997,
        "score": 71.47280957081014,
        "aum_bonus": 0.0,
        "cagr": 0.17585588638772043,
        "alpha": 0.10124666281743525,
        "sortino_ratio": 0.6579446202857921,
        "volatility": 0.15770806830764733,
        "max_drawdown": -0.20996357098926047,
        "calmar_ratio": 0.8375542745780189,
        "rolling_1y_positive_ratio": 0.9493087557603687,
        "rolling_cagr_consistency": 0.8250369191325425,
        "downside_deviation_stability": 0.9976393189675897,
        "return_variance_stability": 0.99994761424681,
        "excess_cagr_vs_benchmark": 0.1121633158380888,
        "benchmark_outperformance_ratio": 0.5510752688172043
      }
    ],
    "Hybrid": [
      {
        "scheme_name": "SBI Balanced Advantage Fund - Direct Plan - Growth",
        "scheme_category": "Hybrid Scheme - Dynamic Asset Allocation or Balanced Advantage",
        "broad_category": "Hybrid",
        "aum_cr": 35454.3902,
        "score": 95.12239290374715,
        "aum_bonus": 3.1223929037471594,
        "cagr": 0.11312899990552161,
        "alpha": 0.04221099675730876,
        "sortino_ratio": 0.7426830630451609,
        "volatility": 0.06342222751210964,
        "max_drawdown": -0.07392584359999058,
        "calmar_ratio": 1.530303807118625,
        "rolling_1y_positive_ratio": 1.0,
        "rolling_cagr_consistency": 0.9278015843127725,
        "downside_deviation_stability": 0.9991593741209488,
        "return_variance_stability": 0.9999918545427345,
        "excess_cagr_vs_benchmark": 0.03881287806925604,
        "benchmark_outperformance_ratio": 0.5180616740088105
      },
      {
        "scheme_name": "SBI EQUITY HYBRID FUND - DIRECT PLAN - Growth",
        "scheme_category": "SBI EQUITY HYBRID FUND - DIRECT PLAN - Growth",
        "broad_category": "Hybrid",
        "aum_cr": 72494.8446,
        "score": 69.84200184790285,
        "aum_bonus": 10.0,
        "cagr": 0.14455898431892322,
        "alpha": 0.04618045786868752,
        "sortino_ratio": 0.6713968407574081,
        "volatility": 0.11172549883899903,
        "max_drawdown": -0.2748953179124069,
        "calmar_ratio": 0.525869212385006,
        "rolling_1y_positive_ratio": 0.9326732673267327,
        "rolling_cagr_consistency": 0.8763797688517692,
        "downside_deviation_stability": 0.9972999313103631,
        "return_variance_stability": 0.9999164899629682,
        "excess_cagr_vs_benchmark": 0.034720146495285986,
        "benchmark_outperformance_ratio": 0.5223926380368098
      },
      {
        "scheme_name": "Kotak Arbitrage Fund - Direct Plan - Growth",
        "scheme_category": "Hybrid Scheme - Arbitrage Fund",
        "broad_category": "Hybrid",
        "aum_cr": 27307.923199999997,
        "score": 36.225486880833074,
        "aum_bonus": 0.6121231060458379,
        "cagr": 0.0708544352494398,
        "alpha": 0.011572348811365228,
        "sortino_ratio": 1.229140115608729,
        "volatility": 0.00998572628047568,
        "max_drawdown": -0.0056836872072952025,
        "calmar_ratio": 10.0,
        "rolling_1y_positive_ratio": 1.0,
        "rolling_cagr_consistency": 0.983499661747419,
        "downside_deviation_stability": 0.9998887446375072,
        "return_variance_stability": 0.9999997830880518,
        "excess_cagr_vs_benchmark": -0.04258971997617711,
        "benchmark_outperformance_ratio": 0.47560222359481164
      }
    ],
    "Debt": [
      {
        "scheme_name": "Aditya Birla Sun Life Savings Fund - Growth - Direct Plan",
        "scheme_category": "Debt Scheme - Ultra Short Duration Fund",
        "broad_category": "Debt",
        "aum_cr": 7823.9556999999995,
        "score": 82.0,
        "aum_bonus": 0.0,
        "cagr": 0.07695680874239086,
        "alpha": 0.017035666468247855,
        "sortino_ratio": 1.5368976789981106,
        "volatility": 0.006475922020121026,
        "max_drawdown": -0.012080617487131618,
        "calmar_ratio": 6.370271124333333,
        "rolling_1y_positive_ratio": 1.0,
        "rolling_cagr_consistency": 0.9824259733158142,
        "downside_deviation_stability": 0.9998327383845295,
        "return_variance_stability": 0.9999995375224077,
        "excess_cagr_vs_benchmark": -0.021511710060182043,
        "benchmark_outperformance_ratio": 0.4809255784865541
      },
      {
        "scheme_name": "HDFC Corporate Bond Fund - Growth Option - Direct Plan",
        "scheme_category": "HDFC Corporate Bond Fund - Growth Option - Direct Plan",
        "broad_category": "Debt",
        "aum_cr": 25623.636000000002,
        "score": 49.78276313292757,
        "aum_bonus": 0.0,
        "cagr": 0.07941206015503899,
        "alpha": 0.01877136192198027,
        "sortino_ratio": 0.8763350749212109,
        "volatility": 0.017780864143134817,
        "max_drawdown": -0.040034480917253486,
        "calmar_ratio": 1.9835916024282738,
        "rolling_1y_positive_ratio": 1.0,
        "rolling_cagr_consistency": 0.9743821886120838,
        "downside_deviation_stability": 0.9994704233419466,
        "return_variance_stability": 0.9999971578674725,
        "excess_cagr_vs_benchmark": -0.019270385849034177,
        "benchmark_outperformance_ratio": 0.4807752422632072
      },
      {
        "scheme_name": "Kotak Bond Short Term Plan-(Growth) - Direct",
        "scheme_category": "Debt Scheme - Short Duration Fund",
        "broad_category": "Debt",
        "aum_cr": 14817.926599999999,
        "score": 54.474756443349726,
        "aum_bonus": 0.0,
        "cagr": 0.07946961561945654,
        "alpha": 0.018908618947707755,
        "sortino_ratio": 0.8993145780907156,
        "volatility": 0.017734681670344372,
        "max_drawdown": -0.03054739886926411,
        "calmar_ratio": 2.6015182490518534,
        "rolling_1y_positive_ratio": 1.0,
        "rolling_cagr_consistency": 0.9761579959608053,
        "downside_deviation_stability": 0.9994373911483441,
        "return_variance_stability": 0.9999965422559949,
        "excess_cagr_vs_benchmark": -0.018976421733900795,
        "benchmark_outperformance_ratio": 0.480450422270879
      },
      {
        "scheme_name": "Nippon India Money Market Fund - Direct Plan Growth Plan - Growth Option",
        "scheme_category": "Nippon India Money Market Fund - Direct Plan Growth Plan - Growth Option",
        "broad_category": "Debt",
        "aum_cr": 5089.2908,
        "score": 43.67245235963694,
        "aum_bonus": 0.0,
        "cagr": 0.07312921796644911,
        "alpha": 0.0024161158184175385,
        "sortino_ratio": 0.6347123333451428,
        "volatility": 0.003993342644543456,
        "max_drawdown": -0.008672644107707007,
        "calmar_ratio": 8.432170980181501,
        "rolling_1y_positive_ratio": 1.0,
        "rolling_cagr_consistency": 0.985740440421616,
        "downside_deviation_stability": 0.99991664087694,
        "return_variance_stability": 0.9999997835710532,
        "excess_cagr_vs_benchmark": -0.04168748712609016,
        "benchmark_outperformance_ratio": 0.478895096213532
      },
      {
        "scheme_name": "ICICI Prudential Money Market Fund Option - Direct Plan -  Growth",
        "scheme_category": "ICICI Prudential Money Market Fund Option - Direct Plan -  Growth",
        "broad_category": "Debt",
        "aum_cr": 8209.6115,
        "score": 39.2048124607189,
        "aum_bonus": 0.0,
        "cagr": 0.07269394452181266,
        "alpha": 0.0019994040177216676,
        "sortino_ratio": 0.5631949065683358,
        "volatility": 0.004779826192439494,
        "max_drawdown": -0.012282069428827126,
        "calmar_ratio": 5.91870490091787,
        "rolling_1y_positive_ratio": 1.0,
        "rolling_cagr_consistency": 0.9868197575548294,
        "downside_deviation_stability": 0.9998921230377519,
        "return_variance_stability": 0.9999995912486189,
        "excess_cagr_vs_benchmark": -0.04333471220568219,
        "benchmark_outperformance_ratio": 0.4788819875776398
      }
    ]
  },
  "aum_diagnostics": {
    "aum_filter_applied": true,
    "aum_filter_bypassed": false,
    "aum_filter_reason": "strict_applied",
    "candidates_before_filter": 59,
    "excluded_for_low_or_missing_aum": 12,
    "survivors_after_filter": 47,
    "threshold_non_debt_15000_pass_count": 30,
    "threshold_debt_5000_pass_count": 17,
    "threshold_25000_pass_count": 18,
    "debt_before_filter": 19,
    "non_debt_before_filter": 40,
    "debt_after_filter": 17,
    "non_debt_after_filter": 30,
    "aum_lookup_coverage": 0.49069508509623033,
    "aum_lookup_matched_count": 3085,
    "aum_lookup_universe_size": 6287,
    "aum_source_hit_counts": {
      "unmatched": 3202,
      "amfi_average_aum": 2809,
      "etmoney": 276
    },
    "aum_filter_threshold_cr_non_debt": 15000.0,
    "aum_filter_threshold_cr_debt": 5000.0,
    "aum_bonus_threshold_cr": 25000.0,
    "aum_bonus_points": 10.0
  }
}